pytorch_trainer/__init__.py
pytorch_trainer/configuration/__init__.py
pytorch_trainer/configuration/dataloader_config.py
pytorch_trainer/configuration/dataset_config.py
pytorch_trainer/configuration/optimizer_config.py
pytorch_trainer/configuration/system_config.py
pytorch_trainer/configuration/traniner_config.py
pytorch_trainer/datasets/__init__.py
pytorch_trainer/datasets/list_dataset.py
pytorch_trainer/hooks/__init__.py
pytorch_trainer/hooks/faster_rcnn_hook.py
pytorch_trainer/hooks/hook_default.py
pytorch_trainer/metrics/__init__.py
pytorch_trainer/metrics/accuracy_estimator.py
pytorch_trainer/metrics/ap_estimator.py
pytorch_trainer/metrics/base_metric.py
pytorch_trainer/trainer/__init__.py
pytorch_trainer/trainer/trainer.py
pytorch_trainer/utils/__init__.py
pytorch_trainer/utils/average_meter.py
pytorch_trainer/utils/dataset_tools.py
pytorch_trainer/utils/path_configs.py
pytorch_trainer/utils/system_system.py
pytorch_trainer/utils/voc_eval.py
pytorch_trainer/visualizer/__init__.py
pytorch_trainer/visualizer/matplotlib_visualizer.py
pytorch_trainer/visualizer/tensorboard_visualizer.py
pytorch_trainer/visualizer/visualizer.py
pytorch_trainer-0.0.5.dist-info/LICENSE
pytorch_trainer-0.0.5.dist-info/METADATA
pytorch_trainer-0.0.5.dist-info/WHEEL
pytorch_trainer-0.0.5.dist-info/top_level.txt
pytorch_trainer-0.0.5.dist-info/RECORD
