Metadata-Version: 2.1
Name: pytorch-trainer
Version: 0.0.5
Summary: A mini training neural networks pipeline skeleton in PyTorch.
Home-page: https://github.com/ShawnZhang31/trainer
Author: Shawn Zhang
Author-email: shawnzhang31@gmail.com
License: MIT
Platform: UNKNOWN
Requires-Python: >=3.0
Requires-Dist: torch (>=1.0)
Requires-Dist: torchvision
Requires-Dist: tqdm
Requires-Dist: tensorboard
Requires-Dist: matplotlib
